qibo_client/__init__.py
qibo_client/config_logging.py
qibo_client/constants.py
qibo_client/exceptions.py
qibo_client/qibo_client.py
qibo_client/qibo_job.py
qibo_client/utils.py
qibo_client-0.2.0.dist-info/METADATA
qibo_client-0.2.0.dist-info/WHEEL
qibo_client-0.2.0.dist-info/licenses/LICENSE
qibo_client-0.2.0.dist-info/RECORD
