Metadata-Version: 2.4
Name: qibo-client
Version: 0.2.0
Summary: Qibo client interface.
License: Apache-2.0
License-File: LICENSE
Author: The Qibo team
Requires-Python: >=3.10,<3.14
Classifier: License :: OSI Approved :: Apache Software License
Classifier: Programming Language :: Python :: 3
Classifier: Programming Language :: Python :: 3.10
Classifier: Programming Language :: Python :: 3.11
Classifier: Programming Language :: Python :: 3.12
Classifier: Programming Language :: Python :: 3.13
Classifier: Topic :: Scientific/Engineering :: Physics
Requires-Dist: packaging (>=24.1,<25.0)
Requires-Dist: python-dateutil (>=2.9.0.post0,<3.0.0)
Requires-Dist: qibo (>=0.2.16,<0.3.0)
Requires-Dist: requests (>=2.31.0,<3.0.0)
Requires-Dist: rich (>=14.1.0,<15.0.0)
Requires-Dist: tabulate (>=0.9.0,<0.10.0)
Project-URL: Documentation, https://qibo.science/qibo-client/stable
Project-URL: Homepage, https://qibo.science/
Project-URL: Repository, https://github.com/qiboteam/qibo-client/
